zandev_textual_widgets/__init__.py
zandev_textual_widgets/dialog.py
zandev_textual_widgets/menu.py
zandev_textual_widgets-1.0.0.dist-info/LICENCE
zandev_textual_widgets-1.0.0.dist-info/METADATA
zandev_textual_widgets-1.0.0.dist-info/WHEEL
zandev_textual_widgets-1.0.0.dist-info/top_level.txt
zandev_textual_widgets-1.0.0.dist-info/RECORD
