Metadata-Version: 2.2
Name: zandev_textual_widgets
Version: 1.0.0
Summary: A selection of widgets for Textual
Author-email: John M Reynolds <zandev@gmail.com>
Project-URL: Homepage, https://github.com/ZandevOxford/zandev_textual_widgets
Project-URL: Issues, https://github.com/ZandevOxford/zandev_textual_widgets/issues
Classifier: Programming Language :: Python :: 3
Classifier: License :: OSI Approved :: MIT License
Classifier: Operating System :: OS Independent
Requires-Python: >=3.8
License-File: LICENCE
Requires-Dist: Textual>=1.0.0
Requires-Dist: pywin32; platform_system == "Windows"
